LICENSE
MANIFEST.in
README.md
requirements.txt
setup.cfg
setup.py
fcn/__init__.py
fcn/data.py
fcn/trainer.py
fcn/utils.py
fcn.egg-info/PKG-INFO
fcn.egg-info/SOURCES.txt
fcn.egg-info/dependency_links.txt
fcn.egg-info/requires.txt
fcn.egg-info/top_level.txt
fcn/datasets/__init__.py
fcn/datasets/transforms.py
fcn/datasets/voc.py
fcn/extensions/__init__.py
fcn/extensions/params_report.py
fcn/extensions/semantic_segmentation_vis_report.py
fcn/external/fcn.berkeleyvision.org/data/pascal/README.md
fcn/external/fcn.berkeleyvision.org/data/pascal/classes.txt
fcn/external/fcn.berkeleyvision.org/data/pascal/seg11valid.txt
fcn/initializers/__init__.py
fcn/initializers/weight.py
fcn/models/__init__.py
fcn/models/fcn16s.py
fcn/models/fcn32s.py
fcn/models/fcn8s.py
fcn/models/vgg16.py
scripts/fcn_infer.py